Javascript20Nian/README.md
Javascript20Nian/__init__.py
Javascript20Nian/__main__.py
Javascript20Nian/file.epub
Javascript20Nian/index.html
Javascript20Nian/css/__init__.py
Javascript20Nian/css/annotations.css
Javascript20Nian/css/main.css
Javascript20Nian/css/normalize.css
Javascript20Nian/css/popup.css
Javascript20Nian/font/__init__.py
Javascript20Nian/font/fontello.eot
Javascript20Nian/font/fontello.svg
Javascript20Nian/font/fontello.ttf
Javascript20Nian/font/fontello.woff
Javascript20Nian/img/__init__.py
Javascript20Nian/img/annotator-glyph-sprite.png
Javascript20Nian/img/annotator-icon-sprite.png
Javascript20Nian/img/apple-touch-icon.png
Javascript20Nian/img/cancelfullscreen.png
Javascript20Nian/img/close.png
Javascript20Nian/img/fullscreen.png
Javascript20Nian/img/loader.gif
Javascript20Nian/img/menu-icon.png
Javascript20Nian/img/save.png
Javascript20Nian/img/saved.png
Javascript20Nian/img/settings-s.png
Javascript20Nian/img/settings.png
Javascript20Nian/img/star.png
Javascript20Nian/js/__init__.py
Javascript20Nian/js/epub.js
Javascript20Nian/js/epub.min.js
Javascript20Nian/js/epub.min.map
Javascript20Nian/js/hooks.min.js
Javascript20Nian/js/hooks.min.map
Javascript20Nian/js/reader.js
Javascript20Nian/js/reader.js.map
Javascript20Nian/js/reader.min.js
Javascript20Nian/js/reader.min.map
Javascript20Nian/js/hooks/__init__.py
Javascript20Nian/js/hooks/extensions/__init__.py
Javascript20Nian/js/hooks/extensions/highlight.js
Javascript20Nian/js/libs/__init__.py
Javascript20Nian/js/libs/jquery.min.js
Javascript20Nian/js/libs/localforage.min.js
Javascript20Nian/js/libs/screenfull.js
Javascript20Nian/js/libs/screenfull.min.js
Javascript20Nian/js/libs/zip.min.js
Javascript20Nian/js/plugins/__init__.py
Javascript20Nian/js/plugins/hypothesis.js
Javascript20Nian/js/plugins/search.js
javascript_20_nian-2024.3.4.0.dist-info/METADATA
javascript_20_nian-2024.3.4.0.dist-info/WHEEL
javascript_20_nian-2024.3.4.0.dist-info/entry_points.txt
javascript_20_nian-2024.3.4.0.dist-info/top_level.txt
javascript_20_nian-2024.3.4.0.dist-info/RECORD
